CTlessPET/__init__.py
CTlessPET/dicom_io.py
CTlessPET/main.py
CTlessPET/utils.py
ctlesspet-0.2.4.dist-info/METADATA
ctlesspet-0.2.4.dist-info/WHEEL
ctlesspet-0.2.4.dist-info/entry_points.txt
ctlesspet-0.2.4.dist-info/licenses/LICENSE
ctlesspet-0.2.4.dist-info/RECORD
