Metadata-Version: 2.4
Name: CTlessPET
Version: 0.2.4
Summary: CTlessPET for synthetic CT from NAC PET data
Project-URL: Homepage, https://github.com/depict-rh/CTlessPET
Project-URL: Issues, https://github.com/depict-rh/CTlessPET/issues
Author-email: Claes Ladefoged <claes.noehr.ladefoged@regionh.dk>
License-File: LICENSE
Classifier: License :: OSI Approved :: MIT License
Classifier: Operating System :: Unix
Classifier: Programming Language :: Python :: 3
Requires-Python: >=3.8
Requires-Dist: dicom2nifti==2.4.9
Requires-Dist: nibabel
Requires-Dist: numpy
Requires-Dist: pydicom==2.4.4
Requires-Dist: torch>=2.5.0
Requires-Dist: torchio
Provides-Extra: gdcm
Requires-Dist: python-gdcm>=3.0.22; extra == 'gdcm'
